plugin.cmake
setup.py
girder_treeview/__init__.py
girder_treeview.egg-info/PKG-INFO
girder_treeview.egg-info/SOURCES.txt
girder_treeview.egg-info/dependency_links.txt
girder_treeview.egg-info/entry_points.txt
girder_treeview.egg-info/not-zip-safe
girder_treeview.egg-info/requires.txt
girder_treeview.egg-info/top_level.txt
girder_treeview/web_client/index.js
girder_treeview/web_client/jstree.js
girder_treeview/web_client/main.js
girder_treeview/web_client/package.json
girder_treeview/web_client/root.js
girder_treeview/web_client/routes.js
girder_treeview/web_client/types.js
girder_treeview/web_client/builtin/collection.js
girder_treeview/web_client/builtin/collections.js
girder_treeview/web_client/builtin/file.js
girder_treeview/web_client/builtin/folder.js
girder_treeview/web_client/builtin/home.js
girder_treeview/web_client/builtin/index.js
girder_treeview/web_client/builtin/item.js
girder_treeview/web_client/builtin/user.js
girder_treeview/web_client/builtin/users.js
girder_treeview/web_client/stylesheets/configView.styl
girder_treeview/web_client/stylesheets/treeDialog.styl
girder_treeview/web_client/templates/configView.pug
girder_treeview/web_client/templates/treeDialog.pug
girder_treeview/web_client/utils/auth.js
girder_treeview/web_client/utils/getNode.js
girder_treeview/web_client/utils/index.js
girder_treeview/web_client/utils/node.js
girder_treeview/web_client/utils/request.js
girder_treeview/web_client/views/ConfigView.js
girder_treeview/web_client/views/FileDialog.js
girder_treeview/web_client/views/FolderDialog.js
girder_treeview/web_client/views/ItemDialog.js
girder_treeview/web_client/views/TreeDialog.js
girder_treeview/web_client/views/TreeView.js
girder_treeview/web_client/views/index.js
plugin_tests/__init__.py
plugin_tests/treeviewWidgetSpec.js
plugin_tests/treeviewWidgetSpec.yml
plugin_tests/typesSpec.js
plugin_tests/files/file.csv
plugin_tests/files/file.gif
plugin_tests/files/file.jpg
plugin_tests/files/file.json
plugin_tests/files/file.png
plugin_tests/files/file.tif
plugin_tests/files/file.txt
plugin_tests/files/file.xml